Chibchas-0.2.18b0.data/scripts/chibchas_institulac
Chibchas-0.2.18b0.data/scripts/chibchas_server
chibchas/JSON_output.ipynb
chibchas/__init__.py
chibchas/dict_tables.json
chibchas/tools.py
chibchas/webapp.py
chibchas/templates/login.html
chibchas/templates/processing.html
chibchas/templates/template_data.xlsx
chibchas/templates/img/logo.jpeg
Chibchas-0.2.18b0.dist-info/LICENSE
Chibchas-0.2.18b0.dist-info/METADATA
Chibchas-0.2.18b0.dist-info/WHEEL
Chibchas-0.2.18b0.dist-info/top_level.txt
Chibchas-0.2.18b0.dist-info/RECORD
