Metadata-Version: 2.1
Name: Chibchas
Version: 0.2.18b0
Summary: InstituLAC Automation Tools
Home-page: https://github.com/colav/Chibchas
Author: Colav
Author-email: colav@udea.edu.co
License: BSD
Classifier: Development Status :: 3 - Alpha
Classifier: Intended Audience :: Developers
Classifier: Topic :: Software Development :: Build Tools
Classifier: License :: OSI Approved :: MIT License
Classifier: Programming Language :: Python :: 3
Classifier: Programming Language :: Python :: 3.9
Classifier: Programming Language :: Python :: 3.10
Classifier: Programming Language :: Python :: 3.11
Requires-Python: >=3.6
License-File: LICENSE
Requires-Dist: flask-wtf
Requires-Dist: wtforms
Requires-Dist: Flask-Bootstrap
Requires-Dist: html5lib
Requires-Dist: pandas
Requires-Dist: numpy
Requires-Dist: helium
Requires-Dist: xlsxwriter
Requires-Dist: lxml
Requires-Dist: bs4
Requires-Dist: xlrd
Requires-Dist: openpyxl
